RTL-Mini-Projects/02-Digital-Stopwatch/03-rtl-tb/digital_stopwatch.v
module digital_stopwatch(
    parameter integer SUBSEC_CYCLES = 100,
    parameter integer MAX_MINUTES = 100
)(
    input clk,
    input reset,
    input start,

    output reg [7:0] minutes,
    output reg [5:0] seconds,
    output reg [6:0] subseconds
);

always @(posedge clk) begin
   if (reset) begin 
       minutes <= 8'd0;
       seconds <= 6'd0;
       subseconds <= 7'd0;
    end

   else if (start) begin
       if (subseconds == SUBSEC_CYCLES -1) begin
           subseconds <= 7'd0;

           if (seconds == 59) begin
               seconds <= 6'd0;

               if (minutes == MAX_MINUTES)
                  minutes <= 8'd0;
               else 
                  minutes <= minutes + 1;   
            end

            else begin
                seconds <= seconds + 1;
            end
        end 
        else begin
            subseconds <= subseconds + 1;
        end
    end 
end
endmodule

RTL-Mini-Projects/02-Digital-Stopwatch/03-rtl-tb/digital_stopwatch_tb.v
module digital_stopwatch_tb;

    // Testbench input signals
    reg clk;
    reg reset;
    reg start;
    
    //DUT output signals
    wire [7:0] minutes;
    wire [5:0] seconds;
    wire [6:0] subseconds;
 
    // Connect testbench to DUT
    digital_stopwatch dut(
        .clk(clk),
        .reset(reset),
        .start(start),
        .minutes(minutes),
        .seconds(seconds),
        .subseconds(subseconds)
    );
  // Generate clock
  initial begin 
    clk = 1'b0;
    forever #5 clk = ~ clk;
  end

  // Create waveform file
  initial begin
      $dumpfile("digital_stopwatch.vcd");
      $dumpvars(0, digital_stopwatch_tb);
  end
  
  // Stop simulation
  initial begin 
      #100;
      $finish;
  end
endmodule

RTL-Mini-Projects/02-Digital-Stopwatch/03-rtl-tb/digital_stopwatch.vcd
$date
	Sun Sep 20 06:47:27 2026
$end
$version
	Icarus Verilog
$end
$timescale
	1s
$end
$scope module digital_stopwatch_tb $end
$var wire 7 ! subseconds [6:0] $end
$var wire 6 " seconds [5:0] $end
$var wire 8 # minutes [7:0] $end
$var reg 1 $ clk $end
$var reg 1 % reset $end
$var reg 1 & start $end
$scope module dut $end
$var wire 1 $ clk $end
$var wire 1 % reset $end
$var wire 1 & start $end
$var parameter 32 ' MAX_MINUTES $end
$var parameter 32 ( SUBSEC_CYCLES $end
$var reg 8 ) minutes [7:0] $end
$var reg 6 * seconds [5:0] $end
$var reg 7 + subseconds [6:0] $end
$upscope $end
$upscope $end
$enddefinitions $end
$comment Show the parameter values. $end
$dumpall
b1100100 (
b1100100 '
$end
#0
$dumpvars
bx +
bx *
bx )
0&
1%
0$
bx #
bx "
bx !
$end
#5
b0 !
b0 +
b0 "
b0 *
b0 #
b0 )
1$
#10
0$
1&
0%
#15
b1 !
b1 +
1$
#20
0$
#25
b10 !
b10 +
1$
#30
0$
#35
b11 !
b11 +
1$
#40
0$
#45
b100 !
b100 +
1$
#50
0$
#55
b101 !
b101 +
1$
#60
0$
#65
b110 !
b110 +
1$
#70
0$
#75
b111 !
b111 +
1$
#80
0$
#85
b1000 !
b1000 +
1$
#90
0$
#95
b1001 !
b1001 +
1$
#100
0$
#105
b1010 !
b1010 +
1$
