RTL-Mini-Projects/01-Traffic-Light-Controller/03-rtl-tb/traffic_light_controller.v
module traffic_light_controller #(
    parameter GREEN_CYCLE = 5,
    parameter YELLOW_CYCLE = 2,
    parameter RED_CYCLE = 1
)
(
    input clk,
    input reset,

    output reg [2:0] north_south,
    output reg [2:0] east_west
);

//Light Encoding
localparam [2:0] RED = 3'b100;
localparam [2:0] YELLOW = 3'b010;
localparam [2:0] GREEN = 3'b001;

// FSM State Encoding
localparam [2:0] NS_GREEN = 3'd0;
localparam [2:0] NS_YELLOW = 3'd1; 
localparam [2:0] ALL_RED_TO_EW = 3'd2;
localparam [2:0] EW_GREEN = 3'd3;
localparam [2:0] EW_YELLOW =3'd4;
localparam [2:0] ALL_RED_TO_NS = 3'd5;

// Internal Registers
reg [2:0] state;
reg [2:0] next_state;
reg [3:0] count;

// 1. State Register + counter
always @(posedge clk) begin

    if (reset) begin
        state <= NS_GREEN;
        count <= 4'd0;
    end

    else begin
        state <= next_state;

        if (state == NS_GREEN) begin
            if (count == GREEN_CYCLE - 1)
                count <= 4'd0;
            else
                count <= count + 4'd1;
        end

        else if (state == NS_YELLOW) begin
            if (count == YELLOW_CYCLE - 1)
                count <= 4'd0;
            else
                count <= count + 4'd1;
        end

        else if (state == ALL_RED_TO_EW) begin
            if (count == RED_CYCLE - 1)
                count <= 4'd0;
            else
                count <= count + 4'd1;
        end

        else if (state == EW_GREEN) begin
            if (count == GREEN_CYCLE - 1)
                count <= 4'd0;
            else
                count <= count + 4'd1;
        end

        else if (state == EW_YELLOW) begin
            if (count == YELLOW_CYCLE - 1)
                count <= 4'd0;
            else
                count <= count + 4'd1;
        end

        else if (state == ALL_RED_TO_NS) begin
            if (count == RED_CYCLE - 1)
                count <= 4'd0;
            else
                count <= count + 4'd1;
        end

        else begin
            count <= 4'd0;
        end
    end

end

// 2. Next State Logic
always @(*) begin
    case (state)
      
        NS_GREEN: begin
            if (count == GREEN_CYCLE -1)
                next_state = NS_YELLOW;
            else 
                next_state = NS_GREEN;
        end              
      
        NS_YELLOW: begin
            if (count == YELLOW_CYCLE -1)
                next_state = ALL_RED_TO_EW;
            else      
                next_state = NS_YELLOW;
        end      

        ALL_RED_TO_EW: begin
            if (count == RED_CYCLE -1)
                next_state = EW_GREEN;
            else
                next_state = ALL_RED_TO_EW;
        end          

        EW_GREEN: begin
            if (count == GREEN_CYCLE -1)
               next_state = EW_YELLOW;
            else
               next_state = EW_GREEN;
        end

        EW_YELLOW: begin
            if (count == YELLOW_CYCLE -1)
                next_state = ALL_RED_TO_NS;
            else
                next_state = EW_YELLOW;
        end

        ALL_RED_TO_NS: begin 
            if (count == RED_CYCLE -1)
                next_state = NS_GREEN;
            else
                next_state = ALL_RED_TO_NS;
        end

        default: begin
            next_state = NS_GREEN;
        end    
    endcase
end

//3. Output Logic
always @(*) begin
    case (state)

        NS_GREEN: begin
            north_south = GREEN;
            east_west = RED;
        end     

        NS_YELLOW: begin
            north_south = YELLOW;
            east_west = RED;
        end            

        ALL_RED_TO_EW: begin
            north_south = RED;
            east_west = RED;
        end    

        EW_GREEN: begin
            north_south = RED;
            east_west = GREEN;
        end    

        EW_YELLOW: begin
            north_south = RED;
            east_west = YELLOW;
        end    

        ALL_RED_TO_NS: begin
            north_south = RED;
            east_west = RED;
        end   

        default: begin
            north_south = RED;
            east_west = RED;
        end
    endcase
end
endmodule

RTL-Mini-Projects/01-Traffic-Light-Controller/03-rtl-tb/traffic_light_controller_tb.v
`timescale 1ns/1ps

module traffic_light_controller_tb;
  
  // Testbench Signals
  reg clk;
  reg reset;
  
  // DUT Output Signals
  wire [2:0] north_south;
  wire [2:0] east_west;

  // DUT Connetions
  traffic_light_controller dut(
    .clk(clk),
    .reset(reset),
    .north_south(north_south),
    .east_west(east_west)
  );

// Clock Generation
initial begin 
    clk = 1'b0;
    forever #5 clk = ~clk;
end    

// Reset
initial begin
    reset = 1'b1;
    #10
    reset = 1'b0;
end    

// Waveform dump
initial begin
    $dumpfile("traffic_light_controller.vcd");
    $dumpvars(0, traffic_light_controller_tb);
end 

//End simulation
initial begin 
    #200;
    $finish;
end

endmodule

RTL-Mini-Projects/01-Traffic-Light-Controller/03-rtl-tb/traffic_light_controller.vcd
$date
	Wed Sep 16 08:28:16 2026
$end
$version
	Icarus Verilog
$end
$timescale
	1ps
$end
$scope module traffic_light_controller_tb $end
$var wire 3 ! north_south [2:0] $end
$var wire 3 " east_west [2:0] $end
$var reg 1 # clk $end
$var reg 1 $ reset $end
$scope module dut $end
$var wire 1 # clk $end
$var wire 1 $ reset $end
$var parameter 3 % ALL_RED_TO_EW $end
$var parameter 3 & ALL_RED_TO_NS $end
$var parameter 3 ' EW_GREEN $end
$var parameter 3 ( EW_YELLOW $end
$var parameter 3 ) GREEN $end
$var parameter 32 * GREEN_CYCLE $end
$var parameter 3 + NS_GREEN $end
$var parameter 3 , NS_YELLOW $end
$var parameter 3 - RED $end
$var parameter 32 . RED_CYCLE $end
$var parameter 3 / YELLOW $end
$var parameter 32 0 YELLOW_CYCLE $end
$var reg 4 1 count [3:0] $end
$var reg 3 2 east_west [2:0] $end
$var reg 3 3 next_state [2:0] $end
$var reg 3 4 north_south [2:0] $end
$var reg 3 5 state [2:0] $end
$upscope $end
$upscope $end
$enddefinitions $end
$comment Show the parameter values. $end
$dumpall
b10 0
b10 /
b1 .
b100 -
b1 ,
b0 +
b101 *
b1 )
b100 (
b11 '
b101 &
b10 %
$end
#0
$dumpvars
bx 5
bx 4
bx 3
bx 2
bx 1
1$
0#
bx "
bx !
$end
#5000
b100 "
b100 2
b1 !
b1 4
b0 3
b0 1
b0 5
1#
#10000
0#
0$
#15000
b1 1
1#
#20000
0#
#25000
b10 1
1#
#30000
0#
#35000
b11 1
1#
#40000
0#
#45000
b1 3
b100 1
1#
#50000
0#
#55000
b10 !
b10 4
b0 1
b1 5
1#
#60000
0#
#65000
b10 3
b1 1
1#
#70000
0#
#75000
b100 !
b100 4
b11 3
b0 1
b10 5
1#
#80000
0#
#85000
b1 "
b1 2
b11 5
1#
#90000
0#
#95000
b1 1
1#
