Verilog-HDL-and-RTL-Design/11-Sequential-RTL/04-Counters/03-Ring-Counter/ring_counter.v
module ring_counter_4bit(
    input clk,
    output reg [3:0] Q
);

initial begin
    Q = 4'b1000;
end

always @(posedge clk) begin
    Q <= {Q[2:0], Q[3]};
end

endmodule

Verilog-HDL-and-RTL-Design/11-Sequential-RTL/04-Counters/03-Ring-Counter/ring_counter_tb.v
module ring_counter_4bit_tb;

reg clk;
wire [3:0] Q;

ring_counter_4bit DUT(
    .clk(clk),
    .Q(Q)
);

// Clock

initial begin
    clk = 0;
    forever #5 clk <= ~clk;
end

initial begin
    $dumpfile("ring_counter_4bit.vcd");
    $dumpvars(0, ring_counter_4bit_tb);

    #100;

    $finish;
end

endmodule

Verilog-HDL-and-RTL-Design/11-Sequential-RTL/04-Counters/03-Ring-Counter/ring_counter_4bit.vcd
$date
	Sun Aug 30 10:09:31 2026
$end
$version
	Icarus Verilog
$end
$timescale
	1s
$end
$scope module ring_counter_4bit_tb $end
$var wire 4 ! Q [3:0] $end
$var reg 1 " clk $end
$scope module DUT $end
$var wire 1 " clk $end
$var reg 4 # Q [3:0] $end
$upscope $end
$upscope $end
$enddefinitions $end
$comment Show the parameter values. $end
$dumpall
$end
#0
$dumpvars
b1000 #
0"
b1000 !
$end
#5
b1 !
b1 #
1"
#10
0"
#15
b10 !
b10 #
1"
#20
0"
#25
b100 !
b100 #
1"
#30
0"
#35
b1000 !
b1000 #
1"
#40
0"
#45
b1 !
b1 #
1"
#50
0"
#55
b10 !
b10 #
1"
#60
0"
#65
b100 !
b100 #
1"
#70
0"
#75
b1000 !
b1000 #
1"
#80
0"
#85
b1 !
b1 #
1"
#90
0"
#95
b10 !
b10 #
1"
