Verilog-HDL-and-RTL-Design/11-Sequential-RTL/02-Flip-Flops/01-D-Flip-Flop/d_flip_flop.v
module d_flip_flop(

    input D, CLK,
    output reg Q,
    output Q_bar

);

assign Q_bar = ~Q;

  always @(posedge CLK) begin
    Q <= D;

  end
endmodule

Verilog-HDL-and-RTL-Design/11-Sequential-RTL/02-Flip-Flops/01-D-Flip-Flop/d_flip_flop_tb.v
module d_flip_flop_tb;
   reg D, CLK;

   wire Q;
   wire Q_bar;

   d_flip_flop DUT(
    .D(D),
    .CLK(CLK),
    .Q(Q),
    .Q_bar(Q_bar)

   );

    // Clock Generation
    initial begin 
      CLK = 0;
        forever #5 CLK = ~CLK;
    end

    initial begin
      $dumpfile("d_flip_flop.vcd");
      $dumpvars(0, d_flip_flop_tb);

      D = 0;

      #10;

      D = 1;

      #10;

      D = 0;

      #10;

      D = 1;

      #10;

      $finish;
    end
endmodule

Verilog-HDL-and-RTL-Design/11-Sequential-RTL/02-Flip-Flops/01-D-Flip-Flop/d_flip_flop.vcd
$date
	Sun Aug 30 06:56:29 2026
$end
$version
	Icarus Verilog
$end
$timescale
	1s
$end
$scope module d_flip_flop_tb $end
$var wire 1 ! Q_bar $end
$var wire 1 " Q $end
$var reg 1 # CLK $end
$var reg 1 $ D $end
$scope module DUT $end
$var wire 1 # CLK $end
$var wire 1 $ D $end
$var wire 1 ! Q_bar $end
$var reg 1 " Q $end
$upscope $end
$upscope $end
$enddefinitions $end
$comment Show the parameter values. $end
$dumpall
$end
#0
$dumpvars
0$
0#
x"
x!
$end
#5
1!
0"
1#
#10
0#
1$
#15
0!
1"
1#
#20
0#
0$
#25
1!
0"
1#
#30
0#
1$
#35
0!
1"
1#
